{
    "oQuery":{
        "estimationNumber": "",
        "request": "",
        "salesOrganization": "",
        "channel": "",
        "iFactor": 0,
        "currency": "",
        "selectSalesOrganization": null,
        "selectRequest": null,
        "selectChannel": null,
        "selectCurrency": null,
        "bToRequiredQuery": true
    },
    "oConfig" : {
        "oAcctionTblItemSalesDocument":{
            "enabled": false
        },
        "oAcctionTblItemSalesDocumentSingle":{
            "enabled": false
        },
        "oAcctionBtnViewSalesCreate":{
            "enabledSalesCreate": false
        },
        "oMessageStripErrorNoValidEstimationNumber": {
            "visible": false
        }

    },
    "iQuantityPartition": 3,
    "oSalesOrder": null,
    "oSelectEstimationNumber" : null,
    "testData":[
        {
            "cod": "1263",
            "nameOrder": "testData"
        }
    ],
    "request":[
        {
            "document": "10245212",
            "name": "Jhon"
        }
    ],
    "salesOrganization":[
        {
            "document": "21551",
            "name": "Mexico DC"
        }
    ],
    "channel":[
        {
            "document": "25",
            "name": "Chiapas"
        }
    ],
    "currency":[
        {"currency": "USD"}
    ]
}